[
  {
    "model": "equipment.mask",
    "pk": 1,
    "fields": {
      "equipment_type": 2,
      "e_number": "BB-1",
      "serial_number": "ABF5F727",
      "status": "Kriticky",
      "located": 1,
      "location": null,
      "type": "MASK-1",
      "rev_2years": "2027-08-19",
      "rev_4years": "2025-01-21",
      "rev_6years": "2026-05-24",
      "extra_1": null,
      "extra_2": null
    }
  },
  {
    "model": "equipment.mask",
    "pk": 2,
    "fields": {
      "equipment_type": 2,
      "e_number": "BB-2",
      "serial_number": "A3D73D82",
      "status": "V rieseni",
      "located": 1,
      "location": null,
      "type": "MASK-2",
      "rev_2years": "2028-07-19",
      "rev_4years": "2028-04-07",
      "rev_6years": "2026-09-28",
      "extra_1": null,
      "extra_2": null
    }
  },
  {
    "model": "equipment.mask",
    "pk": 3,
    "fields": {
      "equipment_type": 2,
      "e_number": "BB-3",
      "serial_number": "67AB51D2",
      "status": "OK",
      "located": 1,
      "location": null,
      "type": "MASK-3",
      "rev_2years": "2024-11-01",
      "rev_4years": "2027-04-14",
      "rev_6years": "2026-06-23",
      "extra_1": null,
      "extra_2": null
    }
  },
  {
    "model": "equipment.mask",
    "pk": 4,
    "fields": {
      "equipment_type": 2,
      "e_number": "BB-4",
      "serial_number": "A4EEA9EA",
      "status": "V rieseni",
      "located": 1,
      "location": null,
      "type": "MASK-4",
      "rev_2years": "2024-11-14",
      "rev_4years": "2024-01-02",
      "rev_6years": "2024-02-17",
      "extra_1": null,
      "extra_2": null
    }
  },
  {
    "model": "equipment.mask",
    "pk": 5,
    "fields": {
      "equipment_type": 2,
      "e_number": "BB-5",
      "serial_number": "CA7E1803",
      "status": "OK",
      "located": 1,
      "location": null,
      "type": "MASK-5",
      "rev_2years": "2025-02-25",
      "rev_4years": "2026-02-14",
      "rev_6years": "2026-07-30",
      "extra_1": null,
      "extra_2": null
    }
  },
  {
    "model": "equipment.mask",
    "pk": 6,
    "fields": {
      "equipment_type": 2,
      "e_number": "BB-6",
      "serial_number": "3281F5F6",
      "status": "BSR",
      "located": 1,
      "location": null,
      "type": "MASK-6",
      "rev_2years": "2027-02-17",
      "rev_4years": "2028-07-21",
      "rev_6years": "2027-10-10",
      "extra_1": null,
      "extra_2": null
    }
  },
  {
    "model": "equipment.mask",
    "pk": 7,
    "fields": {
      "equipment_type": 2,
      "e_number": "BB-7",
      "serial_number": "1DCA7A61",
      "status": "BSR",
      "located": 1,
      "location": null,
      "type": "MASK-7",
      "rev_2years": "2024-02-10",
      "rev_4years": "2024-12-08",
      "rev_6years": "2024-07-13",
      "extra_1": null,
      "extra_2": null
    }
  },
  {
    "model": "equipment.mask",
    "pk": 8,
    "fields": {
      "equipment_type": 2,
      "e_number": "BB-8",
      "serial_number": "1F53F404",
      "status": "BSR",
      "located": 1,
      "location": null,
      "type": "MASK-8",
      "rev_2years": "2027-06-12",
      "rev_4years": "2027-09-23",
      "rev_6years": "2027-02-08",
      "extra_1": null,
      "extra_2": null
    }
  },
  {
    "model": "equipment.ADPMulti",
    "pk": 9,
    "fields": {
      "equipment_type": 3,
      "e_number": "BB-9",
      "serial_number": "FC6CB08F",
      "status": "OK",
      "located": 1,
      "location": null,
      "type": "ADPMULTI-9",
      "rev_1years": "2027-01-18",
      "rev_6years": "2026-06-30"
    }
  },
  {
    "model": "equipment.ADPMulti",
    "pk": 10,
    "fields": {
      "equipment_type": 3,
      "e_number": "BB-10",
      "serial_number": "5ABBA514",
      "status": "Kriticky",
      "located": 1,
      "location": null,
      "type": "ADPMULTI-10",
      "rev_1years": "2025-10-08",
      "rev_6years": "2025-01-13"
    }
  },
  {
    "model": "equipment.ADPMulti",
    "pk": 11,
    "fields": {
      "equipment_type": 3,
      "e_number": "BB-11",
      "serial_number": "11ECA513",
      "status": "V rieseni",
      "located": 1,
      "location": null,
      "type": "ADPMULTI-11",
      "rev_1years": "2026-09-25",
      "rev_6years": "2027-05-14"
    }
  },
  {
    "model": "equipment.ADPMulti",
    "pk": 12,
    "fields": {
      "equipment_type": 3,
      "e_number": "BB-12",
      "serial_number": "B4FDC235",
      "status": "V rieseni",
      "located": 1,
      "location": null,
      "type": "ADPMULTI-12",
      "rev_1years": "2027-02-01",
      "rev_6years": "2025-01-30"
    }
  },
  {
    "model": "equipment.ADPMulti",
    "pk": 13,
    "fields": {
      "equipment_type": 3,
      "e_number": "BB-13",
      "serial_number": "AE72D3EB",
      "status": "OK",
      "located": 1,
      "location": null,
      "type": "ADPMULTI-13",
      "rev_1years": "2024-12-20",
      "rev_6years": "2024-06-14"
    }
  },
  {
    "model": "equipment.ADPMulti",
    "pk": 14,
    "fields": {
      "equipment_type": 3,
      "e_number": "BB-14",
      "serial_number": "BF5FFA0A",
      "status": "Kriticky",
      "located": 1,
      "location": null,
      "type": "ADPMULTI-14",
      "rev_1years": "2024-10-27",
      "rev_6years": "2028-11-14"
    }
  },
  {
    "model": "equipment.ADPMulti",
    "pk": 15,
    "fields": {
      "equipment_type": 3,
      "e_number": "BB-15",
      "serial_number": "915E3B22",
      "status": "OK",
      "located": 1,
      "location": null,
      "type": "ADPMULTI-15",
      "rev_1years": "2026-03-27",
      "rev_6years": "2024-09-30"
    }
  },
  {
    "model": "equipment.ADPMulti",
    "pk": 16,
    "fields": {
      "equipment_type": 3,
      "e_number": "BB-16",
      "serial_number": "4A73C1FD",
      "status": "BSR",
      "located": 1,
      "location": null,
      "type": "ADPMULTI-16",
      "rev_1years": "2025-05-16",
      "rev_6years": "2026-12-10"
    }
  },
  {
    "model": "equipment.ADPSingle",
    "pk": 17,
    "fields": {
      "equipment_type": 3,
      "e_number": "BB-17",
      "serial_number": "3314E34D",
      "status": "V rieseni",
      "located": 1,
      "location": null,
      "type": "ADPSINGLE-17",
      "rev_1years": "2028-11-06",
      "rev_9years": "2025-03-06"
    }
  },
  {
    "model": "equipment.ADPSingle",
    "pk": 18,
    "fields": {
      "equipment_type": 3,
      "e_number": "BB-18",
      "serial_number": "CB26927C",
      "status": "BSR",
      "located": 1,
      "location": null,
      "type": "ADPSINGLE-18",
      "rev_1years": "2025-09-24",
      "rev_9years": "2027-10-06"
    }
  },
  {
    "model": "equipment.ADPSingle",
    "pk": 19,
    "fields": {
      "equipment_type": 3,
      "e_number": "BB-19",
      "serial_number": "404E5C59",
      "status": "OK",
      "located": 1,
      "location": null,
      "type": "ADPSINGLE-19",
      "rev_1years": "2025-08-05",
      "rev_9years": "2025-01-02"
    }
  },
  {
    "model": "equipment.ADPSingle",
    "pk": 20,
    "fields": {
      "equipment_type": 3,
      "e_number": "BB-20",
      "serial_number": "FD58A62C",
      "status": "V rieseni",
      "located": 1,
      "location": null,
      "type": "ADPSINGLE-20",
      "rev_1years": "2027-04-24",
      "rev_9years": "2026-07-30"
    }
  },
  {
    "model": "equipment.ADPSingle",
    "pk": 21,
    "fields": {
      "equipment_type": 3,
      "e_number": "BB-21",
      "serial_number": "116E6A13",
      "status": "BSR",
      "located": 1,
      "location": null,
      "type": "ADPSINGLE-21",
      "rev_1years": "2026-07-08",
      "rev_9years": "2028-03-31"
    }
  },
  {
    "model": "equipment.ADPSingle",
    "pk": 22,
    "fields": {
      "equipment_type": 3,
      "e_number": "BB-22",
      "serial_number": "B9696855",
      "status": "V rieseni",
      "located": 1,
      "location": null,
      "type": "ADPSINGLE-22",
      "rev_1years": "2024-04-22",
      "rev_9years": "2024-01-02"
    }
  },
  {
    "model": "equipment.ADPSingle",
    "pk": 23,
    "fields": {
      "equipment_type": 3,
      "e_number": "BB-23",
      "serial_number": "C3549CBD",
      "status": "OK",
      "located": 1,
      "location": null,
      "type": "ADPSINGLE-23",
      "rev_1years": "2025-10-20",
      "rev_9years": "2026-01-02"
    }
  },
  {
    "model": "equipment.ADPSingle",
    "pk": 24,
    "fields": {
      "equipment_type": 3,
      "e_number": "BB-24",
      "serial_number": "18ED5377",
      "status": "OK",
      "located": 1,
      "location": null,
      "type": "ADPSINGLE-24",
      "rev_1years": "2028-09-16",
      "rev_9years": "2028-01-22"
    }
  },
  {
    "model": "equipment.AirTank",
    "pk": 25,
    "fields": {
      "equipment_type": 6,
      "e_number": "BB-25",
      "serial_number": "F5704CC5",
      "status": "BSR",
      "located": 1,
      "location": null,
      "type": "AIRTANK-25",
      "volume": "8L",
      "material_type": "oceľ",
      "rev_5years": "2026-04-22",
      "made": "2012",
      "service_life": "15"
    }
  },
  {
    "model": "equipment.AirTank",
    "pk": 26,
    "fields": {
      "equipment_type": 6,
      "e_number": "BB-26",
      "serial_number": "989F216E",
      "status": "Kriticky",
      "located": 1,
      "location": null,
      "type": "AIRTANK-26",
      "volume": "8L",
      "material_type": "oceľ",
      "rev_5years": "2024-09-01",
      "made": "2018",
      "service_life": "15"
    }
  },
  {
    "model": "equipment.AirTank",
    "pk": 27,
    "fields": {
      "equipment_type": 6,
      "e_number": "BB-27",
      "serial_number": "26F08EBA",
      "status": "OK",
      "located": 1,
      "location": null,
      "type": "AIRTANK-27",
      "volume": "5L",
      "material_type": "oceľ",
      "rev_5years": "2025-06-28",
      "made": "2000",
      "service_life": "15"
    }
  },
  {
    "model": "equipment.AirTank",
    "pk": 28,
    "fields": {
      "equipment_type": 6,
      "e_number": "BB-28",
      "serial_number": "143C3928",
      "status": "Kriticky",
      "located": 1,
      "location": null,
      "type": "AIRTANK-28",
      "volume": "9L",
      "material_type": "oceľ",
      "rev_5years": "2027-09-26",
      "made": "2001",
      "service_life": "15"
    }
  },
  {
    "model": "equipment.AirTank",
    "pk": 29,
    "fields": {
      "equipment_type": 6,
      "e_number": "BB-29",
      "serial_number": "C23B647A",
      "status": "OK",
      "located": 1,
      "location": null,
      "type": "AIRTANK-29",
      "volume": "2L",
      "material_type": "oceľ",
      "rev_5years": "2027-01-06",
      "made": "2011",
      "service_life": "15"
    }
  },
  {
    "model": "equipment.AirTank",
    "pk": 30,
    "fields": {
      "equipment_type": 6,
      "e_number": "BB-30",
      "serial_number": "DB26D7C8",
      "status": "BSR",
      "located": 1,
      "location": null,
      "type": "AIRTANK-30",
      "volume": "8L",
      "material_type": "oceľ",
      "rev_5years": "2028-07-14",
      "made": "2020",
      "service_life": "15"
    }
  },
  {
    "model": "equipment.AirTank",
    "pk": 31,
    "fields": {
      "equipment_type": 6,
      "e_number": "BB-31",
      "serial_number": "19BAEF89",
      "status": "V rieseni",
      "located": 1,
      "location": null,
      "type": "AIRTANK-31",
      "volume": "6L",
      "material_type": "oceľ",
      "rev_5years": "2028-08-14",
      "made": "2019",
      "service_life": "15"
    }
  },
  {
    "model": "equipment.AirTank",
    "pk": 32,
    "fields": {
      "equipment_type": 6,
      "e_number": "BB-32",
      "serial_number": "F16AD82E",
      "status": "V rieseni",
      "located": 1,
      "location": null,
      "type": "AIRTANK-32",
      "volume": "5L",
      "material_type": "oceľ",
      "rev_5years": "2027-01-06",
      "made": "2013",
      "service_life": "15"
    }
  },
  {
    "model": "equipment.PCHO",
    "pk": 33,
    "fields": {
      "equipment_type": 4,
      "e_number": "BB-33",
      "serial_number": "5EC8A6C1",
      "status": "OK",
      "located": 1,
      "location": null,
      "type": "PCHO-33",
      "rev_half_year": "2026-11-29",
      "rev_2years": "2026-11-20",
      "made": "2022",
      "service_life": "10"
    }
  },
  {
    "model": "equipment.PCHO",
    "pk": 34,
    "fields": {
      "equipment_type": 4,
      "e_number": "BB-34",
      "serial_number": "6E04C58B",
      "status": "V rieseni",
      "located": 1,
      "location": null,
      "type": "PCHO-34",
      "rev_half_year": "2024-03-15",
      "rev_2years": "2027-06-06",
      "made": "2020",
      "service_life": "10"
    }
  },
  {
    "model": "equipment.PCHO",
    "pk": 35,
    "fields": {
      "equipment_type": 4,
      "e_number": "BB-35",
      "serial_number": "38B3DA59",
      "status": "Kriticky",
      "located": 1,
      "location": null,
      "type": "PCHO-35",
      "rev_half_year": "2027-08-07",
      "rev_2years": "2024-11-02",
      "made": "2020",
      "service_life": "10"
    }
  },
  {
    "model": "equipment.PCHO",
    "pk": 36,
    "fields": {
      "equipment_type": 4,
      "e_number": "BB-36",
      "serial_number": "72CEB841",
      "status": "OK",
      "located": 1,
      "location": null,
      "type": "PCHO-36",
      "rev_half_year": "2024-11-18",
      "rev_2years": "2025-05-21",
      "made": "2023",
      "service_life": "10"
    }
  },
  {
    "model": "equipment.PCHO",
    "pk": 37,
    "fields": {
      "equipment_type": 4,
      "e_number": "BB-37",
      "serial_number": "D1B9605C",
      "status": "Kriticky",
      "located": 1,
      "location": null,
      "type": "PCHO-37",
      "rev_half_year": "2026-01-27",
      "rev_2years": "2028-03-27",
      "made": "2020",
      "service_life": "10"
    }
  },
  {
    "model": "equipment.PCHO",
    "pk": 38,
    "fields": {
      "equipment_type": 4,
      "e_number": "BB-38",
      "serial_number": "9BE02E5A",
      "status": "BSR",
      "located": 1,
      "location": null,
      "type": "PCHO-38",
      "rev_half_year": "2025-03-18",
      "rev_2years": "2027-12-29",
      "made": "2020",
      "service_life": "10"
    }
  },
  {
    "model": "equipment.PCHO",
    "pk": 39,
    "fields": {
      "equipment_type": 4,
      "e_number": "BB-39",
      "serial_number": "4746EB30",
      "status": "BSR",
      "located": 1,
      "location": null,
      "type": "PCHO-39",
      "rev_half_year": "2025-01-16",
      "rev_2years": "2027-08-11",
      "made": "2022",
      "service_life": "10"
    }
  },
  {
    "model": "equipment.PCHO",
    "pk": 40,
    "fields": {
      "equipment_type": 4,
      "e_number": "BB-40",
      "serial_number": "3AB0EF31",
      "status": "Kriticky",
      "located": 1,
      "location": null,
      "type": "PCHO-40",
      "rev_half_year": "2027-02-11",
      "rev_2years": "2025-08-17",
      "made": "2023",
      "service_life": "10"
    }
  },
  {
    "model": "equipment.PA",
    "pk": 41,
    "fields": {
      "equipment_type": 5,
      "e_number": "BB-41",
      "serial_number": "D76DE771",
      "status": "V rieseni",
      "located": 1,
      "location": null,
      "type": "PA-41",
      "rev_3year": "2028-03-08",
      "rev_6years": "2027-12-15",
      "rev_9years": "2024-11-03",
      "made": "2013"
    }
  },
  {
    "model": "equipment.PA",
    "pk": 42,
    "fields": {
      "equipment_type": 5,
      "e_number": "BB-42",
      "serial_number": "784C1BAD",
      "status": "V rieseni",
      "located": 1,
      "location": null,
      "type": "PA-42",
      "rev_3year": "2026-01-29",
      "rev_6years": "2026-03-27",
      "rev_9years": "2027-11-10",
      "made": "2022"
    }
  },
  {
    "model": "equipment.PA",
    "pk": 43,
    "fields": {
      "equipment_type": 5,
      "e_number": "BB-43",
      "serial_number": "E7FB695A",
      "status": "Kriticky",
      "located": 1,
      "location": null,
      "type": "PA-43",
      "rev_3year": "2025-10-25",
      "rev_6years": "2026-05-08",
      "rev_9years": "2024-10-21",
      "made": "2022"
    }
  },
  {
    "model": "equipment.PA",
    "pk": 44,
    "fields": {
      "equipment_type": 5,
      "e_number": "BB-44",
      "serial_number": "A3EACBF9",
      "status": "BSR",
      "located": 1,
      "location": null,
      "type": "PA-44",
      "rev_3year": "2024-07-17",
      "rev_6years": "2026-11-24",
      "rev_9years": "2026-04-28",
      "made": "2022"
    }
  },
  {
    "model": "equipment.PA",
    "pk": 45,
    "fields": {
      "equipment_type": 5,
      "e_number": "BB-45",
      "serial_number": "DBCCB853",
      "status": "OK",
      "located": 1,
      "location": null,
      "type": "PA-45",
      "rev_3year": "2028-10-01",
      "rev_6years": "2027-09-07",
      "rev_9years": "2028-06-18",
      "made": "2022"
    }
  }
]